startout/__init__.py
startout/env_manager.py
startout/github_api.py
startout/init_option.py
startout/module.py
startout/paths.py
startout/starterfile.py
startout/tool.py
startout/util.py
startout-0.5.1.dist-info/METADATA
startout-0.5.1.dist-info/WHEEL
startout-0.5.1.dist-info/entry_points.txt
startout-0.5.1.dist-info/RECORD
